pylaunchermpi/__init__.py
pylaunchermpi/main.py
PyLauncherMPI-0.1.8.dist-info/LICENSE
PyLauncherMPI-0.1.8.dist-info/METADATA
PyLauncherMPI-0.1.8.dist-info/WHEEL
PyLauncherMPI-0.1.8.dist-info/entry_points.txt
PyLauncherMPI-0.1.8.dist-info/top_level.txt
PyLauncherMPI-0.1.8.dist-info/RECORD
